INSTALL.txt
LICENSE.txt
MANIFEST.in
README.txt
ez_setup.py
setup.cfg
setup.py
docs/build/dummy
docs/src/apiref.rst
docs/src/conf.py
docs/src/config.rst
docs/src/cpd.rst
docs/src/data.rst
docs/src/devguide.rst
docs/src/discretizer.rst
docs/src/evaluator.rst
docs/src/index.rst
docs/src/install.rst
docs/src/intro.rst
docs/src/network.rst
docs/src/paramref.rst
docs/src/posterior.rst
docs/src/prior.rst
docs/src/result.rst
docs/src/tutorial.rst
docs/src/userguide.rst
docs/src/util.rst
docs/src/learner/exhaustive.rst
docs/src/learner/greedy.rst
docs/src/learner/simanneal.rst
docs/src/static/tutorial/pebl-tutorial-data1.txt
docs/src/static/tutorial/pebl-tutorial-data2.txt
docs/src/static/tutorial/example1-result/index.html
docs/src/static/tutorial/example1-result/data/0-common.png
docs/src/static/tutorial/example1-result/data/0.png
docs/src/static/tutorial/example1-result/data/1-common.png
docs/src/static/tutorial/example1-result/data/1.png
docs/src/static/tutorial/example1-result/data/2-common.png
docs/src/static/tutorial/example1-result/data/2.png
docs/src/static/tutorial/example1-result/data/3-common.png
docs/src/static/tutorial/example1-result/data/3.png
docs/src/static/tutorial/example1-result/data/4-common.png
docs/src/static/tutorial/example1-result/data/4.png
docs/src/static/tutorial/example1-result/data/5-common.png
docs/src/static/tutorial/example1-result/data/5.png
docs/src/static/tutorial/example1-result/data/6-common.png
docs/src/static/tutorial/example1-result/data/6.png
docs/src/static/tutorial/example1-result/data/7-common.png
docs/src/static/tutorial/example1-result/data/7.png
docs/src/static/tutorial/example1-result/data/8-common.png
docs/src/static/tutorial/example1-result/data/8.png
docs/src/static/tutorial/example1-result/data/9-common.png
docs/src/static/tutorial/example1-result/data/9.png
docs/src/static/tutorial/example1-result/data/consensus.0.png
docs/src/static/tutorial/example1-result/data/consensus.1.png
src/pebl.egg-info/PKG-INFO
src/pebl.egg-info/SOURCES.txt
src/pebl.egg-info/dependency_links.txt
src/pebl.egg-info/entry_points.txt
src/pebl.egg-info/not-zip-safe
src/pebl.egg-info/requires.txt
src/pebl.egg-info/top_level.txt
