Metadata-Version: 1.0
Name: pebl
Version: 1.0.2
Summary: Python Environment for Bayesian Learning
Home-page: http://pebl-project.googlecode.com
Author: Abhik Shah
Author-email: abhikshah@gmail.comm
License: MIT
Download-URL: http://pypi.python.org/pypi/pebl
Platform: UNKNOWN
Classifier: Development Status :: 5 - Production/Stable
Classifier: Environment :: Console
Classifier: Intended Audience :: Science/Research
Classifier: License :: OSI Approved :: MIT License
Classifier: Operating System :: OS Independent
Classifier: Programming Language :: Python
Classifier: Topic :: Scientific/Engineering :: Artificial Intelligence
Classifier: Topic :: Scientific/Engineering :: Bio-Informatics
